manilaclient/__init__.py
manilaclient/api_versions.py
manilaclient/base.py
manilaclient/client.py
manilaclient/config.py
manilaclient/exceptions.py
manilaclient/extension.py
manilaclient/shell.py
manilaclient/utils.py
manilaclient/common/__init__.py
manilaclient/common/_i18n.py
manilaclient/common/cliutils.py
manilaclient/common/constants.py
manilaclient/common/httpclient.py
manilaclient/common/apiclient/__init__.py
manilaclient/common/apiclient/base.py
manilaclient/common/apiclient/exceptions.py
manilaclient/common/apiclient/utils.py
manilaclient/tests/__init__.py
manilaclient/tests/functional/__init__.py
manilaclient/tests/functional/base.py
manilaclient/tests/functional/client.py
manilaclient/tests/functional/exceptions.py
manilaclient/tests/functional/test_availability_zones.py
manilaclient/tests/functional/test_common.py
manilaclient/tests/functional/test_export_locations.py
manilaclient/tests/functional/test_limits.py
manilaclient/tests/functional/test_messages.py
manilaclient/tests/functional/test_quotas.py
manilaclient/tests/functional/test_scheduler_stats.py
manilaclient/tests/functional/test_security_services.py
manilaclient/tests/functional/test_services.py
manilaclient/tests/functional/test_share_access.py
manilaclient/tests/functional/test_share_networks.py
manilaclient/tests/functional/test_share_replica_export_locations.py
manilaclient/tests/functional/test_share_servers.py
manilaclient/tests/functional/test_share_types.py
manilaclient/tests/functional/test_shares.py
manilaclient/tests/functional/test_shares_listing.py
manilaclient/tests/functional/test_shares_metadata.py
manilaclient/tests/functional/test_snapshot_access.py
manilaclient/tests/functional/test_snapshot_instances.py
manilaclient/tests/functional/test_snapshot_instances_export_locations.py
manilaclient/tests/functional/test_snapshots_export_locations.py
manilaclient/tests/functional/utils.py
manilaclient/tests/unit/__init__.py
manilaclient/tests/unit/fakes.py
qh_python_manilaclient-0.0.1.dev1.dist-info/AUTHORS
qh_python_manilaclient-0.0.1.dev1.dist-info/LICENSE
qh_python_manilaclient-0.0.1.dev1.dist-info/METADATA
qh_python_manilaclient-0.0.1.dev1.dist-info/WHEEL
qh_python_manilaclient-0.0.1.dev1.dist-info/entry_points.txt
qh_python_manilaclient-0.0.1.dev1.dist-info/pbr.json
qh_python_manilaclient-0.0.1.dev1.dist-info/top_level.txt
qh_python_manilaclient-0.0.1.dev1.dist-info/RECORD
