Metadata-Version: 2.1
Name: qh-python-manilaclient
Version: 0.0.1.dev1
Summary: Client library for OpenStack Manila API.
Home-page: https://docs.openstack.org/python-manilaclient/latest/
Author: OpenStack
Author-email: openstack-discuss@lists.openstack.org
License: UNKNOWN
Platform: UNKNOWN
Classifier: Development Status :: 5 - Production/Stable
Classifier: Environment :: Console
Classifier: Environment :: OpenStack
Classifier: Intended Audience :: Developers
Classifier: Intended Audience :: Information Technology
Classifier: License :: OSI Approved :: Apache Software License
Classifier: Operating System :: OS Independent
Classifier: Programming Language :: Python
Classifier: Programming Language :: Python :: 2
Classifier: Programming Language :: Python :: 2.7
Classifier: Programming Language :: Python :: 3
Classifier: Programming Language :: Python :: 3.5
Classifier: Programming Language :: Python :: 3.6
Requires-Dist: pbr (!=2.1.0,>=2.0.0)
Requires-Dist: oslo.config (>=5.2.0)
Requires-Dist: oslo.log (>=3.36.0)
Requires-Dist: oslo.serialization (!=2.19.1,>=2.18.0)
Requires-Dist: oslo.utils (>=3.33.0)
Requires-Dist: PrettyTable (<0.8,>=0.7.1)
Requires-Dist: requests (>=2.14.2)
Requires-Dist: simplejson (>=3.5.1)
Requires-Dist: Babel (!=2.4.0,>=2.3.4)
Requires-Dist: six (>=1.10.0)
Requires-Dist: python-keystoneclient (>=3.8.0)
Requires-Dist: debtcollector (>=1.2.0)
Requires-Dist: docutils (>=0.11)
Requires-Dist: ipaddress (>=1.0.17) ; (python_version<'3.3')
